[
  {
    "inputs": [
      {
        "internalType": "address",
        "name": "_token",
        "type": "address"
      }
    ],
    "stateMutability": "nonpayable",
    "type": "constructor"
  },
  {
    "anonymous": false,
    "inputs": [
      {
        "indexed": false,
        "internalType": "uint32",
        "name": "_id",
        "type": "uint32"
      },
      {
        "indexed": false,
        "internalType": "uint256",
        "name": "start",
        "type": "uint256"
      },
      {
        "indexed": false,
        "internalType": "uint256",
        "name": "expire",
        "type": "uint256"
      }
    ],
    "name": "ModifyExpireProposal",
    "type": "event"
  },
  {
    "anonymous": false,
    "inputs": [
      {
        "indexed": false,
        "internalType": "uint32",
        "name": "_id",
        "type": "uint32"
      },
      {
        "indexed": false,
        "internalType": "string",
        "name": "title",
        "type": "string"
      },
      {
        "indexed": false,
        "internalType": "uint256",
        "name": "start",
        "type": "uint256"
      },
      {
        "indexed": false,
        "internalType": "uint256",
        "name": "expire",
        "type": "uint256"
      }
    ],
    "name": "NewProposal",
    "type": "event"
  },
  {
    "anonymous": false,
    "inputs": [
      {
        "indexed": true,
        "internalType": "bytes32",
        "name": "role",
        "type": "bytes32"
      },
      {
        "indexed": true,
        "internalType": "bytes32",
        "name": "previousAdminRole",
        "type": "bytes32"
      },
      {
        "indexed": true,
        "internalType": "bytes32",
        "name": "newAdminRole",
        "type": "bytes32"
      }
    ],
    "name": "RoleAdminChanged",
    "type": "event"
  },
  {
    "anonymous": false,
    "inputs": [
      {
        "indexed": true,
        "internalType": "bytes32",
        "name": "role",
        "type": "bytes32"
      },
      {
        "indexed": true,
        "internalType": "address",
        "name": "account",
        "type": "address"
      },
      {
        "indexed": true,
        "internalType": "address",
        "name": "sender",
        "type": "address"
      }
    ],
    "name": "RoleGranted",
    "type": "event"
  },
  {
    "anonymous": false,
    "inputs": [
      {
        "indexed": true,
        "internalType": "bytes32",
        "name": "role",
        "type": "bytes32"
      },
      {
        "indexed": true,
        "internalType": "address",
        "name": "account",
        "type": "address"
      },
      {
        "indexed": true,
        "internalType": "address",
        "name": "sender",
        "type": "address"
      }
    ],
    "name": "RoleRevoked",
    "type": "event"
  },
  {
    "anonymous": false,
    "inputs": [
      {
        "indexed": false,
        "internalType": "address",
        "name": "holder",
        "type": "address"
      },
      {
        "indexed": false,
        "internalType": "uint32",
        "name": "_id",
        "type": "uint32"
      },
      {
        "indexed": false,
        "internalType": "enum Voting.VotingOption",
        "name": "value",
        "type": "uint8"
      },
      {
        "indexed": false,
        "internalType": "uint256",
        "name": "_amount",
        "type": "uint256"
      }
    ],
    "name": "Vote",
    "type": "event"
  },
  {
    "inputs": [],
    "name": "DEFAULT_ADMIN_ROLE",
    "outputs": [
      {
        "internalType": "bytes32",
        "name": "",
        "type": "bytes32"
      }
    ],
    "stateMutability": "view",
    "type": "function"
  },
  {
    "inputs": [],
    "name": "Token",
    "outputs": [
      {
        "internalType": "address",
        "name": "",
        "type": "address"
      }
    ],
    "stateMutability": "view",
    "type": "function"
  },
  {
    "inputs": [
      {
        "internalType": "uint32",
        "name": "proposalId",
        "type": "uint32"
      },
      {
        "internalType": "string",
        "name": "title",
        "type": "string"
      },
      {
        "internalType": "uint256",
        "name": "startTime",
        "type": "uint256"
      },
      {
        "internalType": "uint256",
        "name": "expiration",
        "type": "uint256"
      }
    ],
    "name": "addProposal",
    "outputs": [],
    "stateMutability": "nonpayable",
    "type": "function"
  },
  {
    "inputs": [
      {
        "internalType": "uint32",
        "name": "proposalId",
        "type": "uint32"
      },
      {
        "internalType": "address",
        "name": "_who",
        "type": "address"
      }
    ],
    "name": "canVote",
    "outputs": [
      {
        "internalType": "bool",
        "name": "",
        "type": "bool"
      }
    ],
    "stateMutability": "view",
    "type": "function"
  },
  {
    "inputs": [
      {
        "internalType": "uint32",
        "name": "proposalId",
        "type": "uint32"
      }
    ],
    "name": "getProposal",
    "outputs": [
      {
        "internalType": "uint32",
        "name": "",
        "type": "uint32"
      },
      {
        "internalType": "string",
        "name": "",
        "type": "string"
      },
      {
        "internalType": "uint256",
        "name": "",
        "type": "uint256"
      },
      {
        "internalType": "uint256",
        "name": "",
        "type": "uint256"
      }
    ],
    "stateMutability": "view",
    "type": "function"
  },
  {
    "inputs": [
      {
        "internalType": "bytes32",
        "name": "role",
        "type": "bytes32"
      }
    ],
    "name": "getRoleAdmin",
    "outputs": [
      {
        "internalType": "bytes32",
        "name": "",
        "type": "bytes32"
      }
    ],
    "stateMutability": "view",
    "type": "function"
  },
  {
    "inputs": [
      {
        "internalType": "bytes32",
        "name": "role",
        "type": "bytes32"
      },
      {
        "internalType": "address",
        "name": "account",
        "type": "address"
      }
    ],
    "name": "grantRole",
    "outputs": [],
    "stateMutability": "nonpayable",
    "type": "function"
  },
  {
    "inputs": [
      {
        "internalType": "bytes32",
        "name": "role",
        "type": "bytes32"
      },
      {
        "internalType": "address",
        "name": "account",
        "type": "address"
      }
    ],
    "name": "hasRole",
    "outputs": [
      {
        "internalType": "bool",
        "name": "",
        "type": "bool"
      }
    ],
    "stateMutability": "view",
    "type": "function"
  },
  {
    "inputs": [
      {
        "internalType": "uint32",
        "name": "proposalId",
        "type": "uint32"
      }
    ],
    "name": "isVotingOpen",
    "outputs": [
      {
        "internalType": "bool",
        "name": "",
        "type": "bool"
      }
    ],
    "stateMutability": "view",
    "type": "function"
  },
  {
    "inputs": [
      {
        "internalType": "uint32",
        "name": "proposalId",
        "type": "uint32"
      },
      {
        "internalType": "uint256",
        "name": "startTime",
        "type": "uint256"
      },
      {
        "internalType": "uint256",
        "name": "expiration",
        "type": "uint256"
      }
    ],
    "name": "modifyProposal",
    "outputs": [],
    "stateMutability": "nonpayable",
    "type": "function"
  },
  {
    "inputs": [],
    "name": "owner",
    "outputs": [
      {
        "internalType": "address",
        "name": "",
        "type": "address"
      }
    ],
    "stateMutability": "view",
    "type": "function"
  },
  {
    "inputs": [
      {
        "internalType": "uint32",
        "name": "",
        "type": "uint32"
      }
    ],
    "name": "proposals",
    "outputs": [
      {
        "internalType": "uint32",
        "name": "id",
        "type": "uint32"
      },
      {
        "internalType": "string",
        "name": "title",
        "type": "string"
      },
      {
        "internalType": "uint256",
        "name": "voteCountYes",
        "type": "uint256"
      },
      {
        "internalType": "uint256",
        "name": "voteCountNo",
        "type": "uint256"
      },
      {
        "internalType": "uint256",
        "name": "startDate",
        "type": "uint256"
      },
      {
        "internalType": "uint256",
        "name": "expirationDate",
        "type": "uint256"
      }
    ],
    "stateMutability": "view",
    "type": "function"
  },
  {
    "inputs": [
      {
        "internalType": "bytes32",
        "name": "role",
        "type": "bytes32"
      },
      {
        "internalType": "address",
        "name": "account",
        "type": "address"
      }
    ],
    "name": "renounceRole",
    "outputs": [],
    "stateMutability": "nonpayable",
    "type": "function"
  },
  {
    "inputs": [
      {
        "internalType": "bytes32",
        "name": "role",
        "type": "bytes32"
      },
      {
        "internalType": "address",
        "name": "account",
        "type": "address"
      }
    ],
    "name": "revokeRole",
    "outputs": [],
    "stateMutability": "nonpayable",
    "type": "function"
  },
  {
    "inputs": [
      {
        "internalType": "bytes4",
        "name": "interfaceId",
        "type": "bytes4"
      }
    ],
    "name": "supportsInterface",
    "outputs": [
      {
        "internalType": "bool",
        "name": "",
        "type": "bool"
      }
    ],
    "stateMutability": "view",
    "type": "function"
  },
  {
    "inputs": [
      {
        "internalType": "uint32",
        "name": "proposalId",
        "type": "uint32"
      },
      {
        "internalType": "enum Voting.VotingOption",
        "name": "_vote",
        "type": "uint8"
      }
    ],
    "name": "vote",
    "outputs": [
      {
        "internalType": "uint256",
        "name": "",
        "type": "uint256"
      }
    ],
    "stateMutability": "nonpayable",
    "type": "function"
  },
  {
    "inputs": [
      {
        "internalType": "uint32",
        "name": "proposalId",
        "type": "uint32"
      },
      {
        "internalType": "uint256",
        "name": "_expectedVotingAmount",
        "type": "uint256"
      }
    ],
    "name": "votingPercentages",
    "outputs": [
      {
        "internalType": "uint256",
        "name": "noPercent",
        "type": "uint256"
      },
      {
        "internalType": "uint256",
        "name": "noVotes",
        "type": "uint256"
      },
      {
        "internalType": "uint256",
        "name": "yesPercent",
        "type": "uint256"
      },
      {
        "internalType": "uint256",
        "name": "yesVotes",
        "type": "uint256"
      },
      {
        "internalType": "uint256",
        "name": "totalVoted",
        "type": "uint256"
      },
      {
        "internalType": "uint256",
        "name": "turnoutPercent",
        "type": "uint256"
      }
    ],
    "stateMutability": "view",
    "type": "function"
  }
]
